agentport/__init__.py
agentport/cli.py
agentport/agents/base.py
agentport/agents/runner.py
agentport/agents/simple_openai_agent.py
agentport/core/__init__.py
agentport/core/base_protocol.py
agentport/core/base_protocol_adapter.py
agentport/core/client.py
agentport/core/connector.py
agentport/core/network.py
agentport/core/system_commands.py
agentport/launchers/__init__.py
agentport/launchers/discovery_connector.py
agentport/launchers/network_launcher.py
agentport/launchers/terminal_console.py
agentport/models/__init__.py
agentport/models/manifest.py
agentport/models/message_thread.py
agentport/models/messages.py
agentport/models/network_config.py
agentport/models/network_profile.py
agentport/models/tool.py
agentport/protocols/__init__.py
agentport/protocols/communication/__init__.py
agentport/protocols/communication/simple_messaging/__init__.py
agentport/protocols/communication/simple_messaging/adapter.py
agentport/protocols/communication/simple_messaging/protocol.py
agentport/protocols/discovery/__init__.py
agentport/protocols/discovery/agent_discovery/__init__.py
agentport/protocols/discovery/agent_discovery/adapter.py
agentport/protocols/discovery/agent_discovery/protocol.py
agentport/utils/__init__.py
agentport/utils/message_util.py
agentport/utils/network_discovey.py
agentport/utils/protocol_loaders.py
agentport-0.4.0.dist-info/licenses/LICENSE
openagents/__init__.py
openagents/cli.py
openagents/agents/base.py
openagents/agents/runner.py
openagents/agents/simple_openai_agent.py
openagents/core/__init__.py
openagents/core/base_protocol.py
openagents/core/base_protocol_adapter.py
openagents/core/client.py
openagents/core/connector.py
openagents/core/network.py
openagents/core/system_commands.py
openagents/launchers/__init__.py
openagents/launchers/discovery_connector.py
openagents/launchers/network_launcher.py
openagents/launchers/terminal_console.py
openagents/models/__init__.py
openagents/models/manifest.py
openagents/models/message_thread.py
openagents/models/messages.py
agentport-0.4.0.dist-info/METADATA
agentport-0.4.0.dist-info/WHEEL
agentport-0.4.0.dist-info/entry_points.txt
agentport-0.4.0.dist-info/top_level.txt
agentport-0.4.0.dist-info/RECORD
